smcpy/__init__.py
smcpy/hierarch_log_likelihoods.py
smcpy/log_likelihoods.py
smcpy/paths.py
smcpy/priors.py
smcpy/proposals.py
smcpy/resampler_rngs.py
smcpy/mcmc/__init__.py
smcpy/mcmc/kernel_base.py
smcpy/mcmc/parallel_vector_mcmc.py
smcpy/mcmc/vector_mcmc.py
smcpy/mcmc/vector_mcmc_kernel.py
smcpy/smc/__init__.py
smcpy/smc/initializer.py
smcpy/smc/mutator.py
smcpy/smc/particles.py
smcpy/smc/samplers.py
smcpy/smc/updater.py
smcpy/utils/__init__.py
smcpy/utils/checks.py
smcpy/utils/context_manager.py
smcpy/utils/geweke.py
smcpy/utils/intervals.py
smcpy/utils/mpi_utils.py
smcpy/utils/noise_generator.py
smcpy/utils/plotter.py
smcpy/utils/progress_bar.py
smcpy/utils/properties.py
smcpy/utils/single_rank_comm.py
smcpy/utils/storage.py
smcpy-0.1.11.dist-info/licenses/LICENSE
smcpy-0.1.11.dist-info/METADATA
smcpy-0.1.11.dist-info/WHEEL
smcpy-0.1.11.dist-info/top_level.txt
smcpy-0.1.11.dist-info/RECORD
