Metadata-Version: 2.4
Name: smcpy
Version: 0.1.11
Summary: A package for performing uncertainty quantification using a parallelized sequential Monte Carlo sampler.
Author-email: Patrick Leser <patrick.e.leser@nasa.gov>
License: NOSA v1.3
Project-URL: Homepage, https://github.com/nasa/SMCPy
Project-URL: Repository, https://github.com/nasa/SMCPy
Classifier: Programming Language :: Python :: 3
Classifier: Operating System :: OS Independent
Classifier: Development Status :: 3 - Alpha
Requires-Python: >=3.6
License-File: LICENSE
Requires-Dist: numpy
Requires-Dist: h5py
Requires-Dist: matplotlib
Requires-Dist: tqdm
Requires-Dist: scipy
Requires-Dist: pandas
Requires-Dist: seaborn
Provides-Extra: dev
Requires-Dist: pytest; extra == "dev"
Requires-Dist: pytest-mock; extra == "dev"
Dynamic: license-file
